Metadata-Version: 1.1
Name: context-loop
Version: 0.1.1
Summary: Context manager for asyncio event loop.
Home-page: https://github.com/pawelzny/context-loop
Author: Paweł Zadrożny
Author-email: pawel.zny@gmail.com
License: MIT
Keywords: context,manager,asyncio,event,loop,utility
Platform: UNKNOWN
Classifier: Development Status :: 3 - Alpha
Classifier: Intended Audience :: Developers
Classifier: Natural Language :: English
Classifier: Topic :: Software Development
Classifier: Topic :: Software Development :: Libraries :: Python Modules
Classifier: Programming Language :: Python :: 3.5
Classifier: Programming Language :: Python :: 3.6
Classifier: Programming Language :: Python :: 3 :: Only
Classifier: Programming Language :: Python :: Implementation :: CPython
Classifier: Programming Language :: Python :: Implementation :: PyPy
Classifier: Framework :: AsyncIO
Classifier: License :: OSI Approved :: MIT License
